MANIFEST.in
README.rst
requirements-docs.txt
requirements-test.txt
requirements.txt
setup.cfg
setup.py
src/django_thumbnailfield.egg-info/PKG-INFO
src/django_thumbnailfield.egg-info/SOURCES.txt
src/django_thumbnailfield.egg-info/dependency_links.txt
src/django_thumbnailfield.egg-info/requires.txt
src/django_thumbnailfield.egg-info/top_level.txt
src/django_thumbnailfield.egg-info/zip-safe
src/thumbnailfield/__init__.py
src/thumbnailfield/compatibility.py
src/thumbnailfield/conf.py
src/thumbnailfield/fields.py
src/thumbnailfield/models.py
src/thumbnailfield/process_methods.py
src/thumbnailfield/utils.py
src/thumbnailfield/tests/__init__.py
src/thumbnailfield/tests/models.py
src/thumbnailfield/tests/test_doctests.py
src/thumbnailfield/tests/test_thubmanilfield.py